prynt/__init__.py
prynt/prynt.py
prynter/__init__.py
prynter/__main__.py
prynter/interpreter.py
prynter/prynt.py
prynter-0.2.dist-info/METADATA
prynter-0.2.dist-info/RECORD
prynter-0.2.dist-info/WHEEL
prynter-0.2.dist-info/top_level.txt
