Metadata-Version: 2.1
Name: prynter
Version: 0.2
Summary: Small utility to execute short python commands
Home-page: https://github.com/kanales/prynter
Author: Iván Canales
Author-email: kanales.contact@gmail.com
License: UNKNOWN
Platform: UNKNOWN
Classifier: Programming Language :: Python :: 3
Classifier: License :: OSI Approved :: MIT License
Classifier: Operating System :: OS Independent
